{
  "hoy": [
    {
      "hora": "06:00",
      "viento": "8.1 km/h",
      "oleaje": "1.0 m",
      "direccionOleaje": "Suroeste",
      "temperatura": "10.5°C",
      "direccionViento": "Este",
      "direccionVientoGrados": 107,
      "nivel": "Intermedio",
      "condiciones": "Las condiciones son adecuadas para remadores intermedios, pero se recomienda estar atentos a los cambios en el viento."
    },
    {
      "hora": "09:00",
      "viento": "8.0 km/h",
      "oleaje": "0.98 m",
      "direccionOleaje": "Suroeste",
      "temperatura": "11.8°C",
      "direccionViento": "Este",
      "direccionVientoGrados": 100,
      "nivel": "Intermedio",
      "condiciones": "Ideal para quienes tienen algo de experiencia, aunque el oleaje puede ser un poco desafiante."
    },
    {
      "hora": "12:00",
      "viento": "10.7 km/h",
      "oleaje": "0.96 m",
      "direccionOleaje": "Suroeste",
      "temperatura": "16.3°C",
      "direccionViento": "Oeste",
      "direccionVientoGrados": 250,
      "nivel": "Intermedio",
      "condiciones": "Las condiciones son buenas para intermedios, pero se aconseja mantener el control ante el aumento del viento."
    },
    {
      "hora": "15:00",
      "viento": "16.8 km/h",
      "oleaje": "0.96 m",
      "direccionOleaje": "Suroeste",
      "temperatura": "17.0°C",
      "direccionViento": "Suroeste",
      "direccionVientoGrados": 237,
      "nivel": "Intermedio",
      "condiciones": "Requiere mayor habilidad, ya que el viento puede dificultar el manejo de la tabla."
    },
    {
      "hora": "18:00",
      "viento": "16.3 km/h",
      "oleaje": "0.98 m",
      "direccionOleaje": "Suroeste",
      "temperatura": "14.7°C",
      "direccionViento": "Suroeste",
      "direccionVientoGrados": 213,
      "nivel": "Intermedio",
      "condiciones": "Condiciones retadoras para intermedios, se recomienda estar preparado para el oleaje y el viento."
    },
    {
      "hora": "21:00",
      "viento": "11.5 km/h",
      "oleaje": "0.98 m",
      "direccionOleaje": "Suroeste",
      "temperatura": "12.4°C",
      "direccionViento": "Sur",
      "direccionVientoGrados": 166,
      "nivel": "Intermedio",
      "condiciones": "A pesar de ser intermedio, el viento puede ser un factor a considerar para mantener la estabilidad."
    }
  ],
  "mañana": [
    {
      "hora": "06:00",
      "viento": "8.3 km/h",
      "oleaje": "0.98 m",
      "direccionOleaje": "Suroeste",
      "temperatura": "9.1°C",
      "direccionViento": "Este",
      "direccionVientoGrados": 104,
      "nivel": "Intermedio",
      "condiciones": "Condiciones adecuadas para intermedios, pero con atención al oleaje que puede ser un poco inestable."
    },
    {
      "hora": "09:00",
      "viento": "5.8 km/h",
      "oleaje": "0.96 m",
      "direccionOleaje": "Suroeste",
      "temperatura": "11.8°C",
      "direccionViento": "Sur",
      "direccionVientoGrados": 171,
      "nivel": "Intermedio",
      "condiciones": "Las condiciones son favorables para intermedios, con un viento suave que facilita la navegación."
    },
    {
      "hora": "12:00",
      "viento": "12.7 km/h",
      "oleaje": "0.96 m",
      "direccionOleaje": "Suroeste",
      "temperatura": "16.5°C",
      "direccionViento": "Suroeste",
      "direccionVientoGrados": 232,
      "nivel": "Intermedio",
      "condiciones": "Condiciones adecuadas, pero se recomienda estar alerta ante posibles cambios en el viento."
    },
    {
      "hora": "15:00",
      "viento": "17.9 km/h",
      "oleaje": "0.96 m",
      "direccionOleaje": "Suroeste",
      "temperatura": "17.1°C",
      "direccionViento": "Suroeste",
      "direccionVientoGrados": 218,
      "nivel": "Intermedio",
      "condiciones": "El viento fuerte puede ser un desafío, ideal para remadores con experiencia en condiciones variables."
    },
    {
      "hora": "18:00",
      "viento": "16.9 km/h",
      "oleaje": "0.98 m",
      "direccionOleaje": "Suroeste",
      "temperatura": "14.6°C",
      "direccionViento": "Suroeste",
      "direccionVientoGrados": 203,
      "nivel": "Intermedio",
      "condiciones": "Condiciones que requieren atención, el viento y el oleaje pueden complicar la navegación."
    },
    {
      "hora": "21:00",
      "viento": "13.9 km/h",
      "oleaje": "1.02 m",
      "direccionOleaje": "Suroeste",
      "temperatura": "12.5°C",
      "direccionViento": "Sur",
      "direccionVientoGrados": 166,
      "nivel": "Intermedio",
      "condiciones": "Requiere experiencia, ya que el oleaje puede ser un poco más desafiante para los intermedios."
    }
  ],
  "generado": "2026-05-21 06:37:50",
  "mareas": [
    {
      "hora": "05:50",
      "altura": 1.2,
      "tipo": "alta"
    },
    {
      "hora": "12:02",
      "altura": 0.6,
      "tipo": "baja"
    },
    {
      "hora": "18:15",
      "altura": 1.1,
      "tipo": "alta"
    },
    {
      "hora": "00:27",
      "altura": 0.5,
      "tipo": "baja"
    }
  ]
}