{
  "hoy": [
    {
      "hora": "06:00",
      "viento": "12 km/h",
      "direccionViento": "Sur",
      "direccionVientoGrados": 196,
      "oleaje": "0.94 m",
      "direccionOleaje": "Suroeste",
      "temperatura": "14.6°C",
      "condiciones": "Con viento moderado y oleaje bajo, es adecuado para principiantes.",
      "nivel": "Principiante"
    },
    {
      "hora": "09:00",
      "viento": "10.7 km/h",
      "direccionViento": "Sur",
      "direccionVientoGrados": 192,
      "oleaje": "1.02 m",
      "direccionOleaje": "Suroeste",
      "temperatura": "14.4°C",
      "condiciones": "Con viento ligero y oleaje moderado, es un buen momento para practicar SUP.",
      "nivel": "Principiante"
    },
    {
      "hora": "12:00",
      "viento": "17.3 km/h",
      "direccionViento": "Suroeste",
      "direccionVientoGrados": 234,
      "oleaje": "1.32 m",
      "direccionOleaje": "Suroeste",
      "temperatura": "15.4°C",
      "condiciones": "Con viento fuerte y oleaje moderado, se recomienda precaución para principiantes.",
      "nivel": "Intermedio"
    },
    {
      "hora": "15:00",
      "viento": "15.8 km/h",
      "direccionViento": "Oeste",
      "direccionVientoGrados": 249,
      "oleaje": "1.54 m",
      "direccionOleaje": "Suroeste",
      "temperatura": "15.4°C",
      "condiciones": "Con viento moderado y oleaje moderado, es un momento adecuado para practicar SUP.",
      "nivel": "Principiante"
    },
    {
      "hora": "18:00",
      "viento": "14.7 km/h",
      "direccionViento": "Suroeste",
      "direccionVientoGrados": 239,
      "oleaje": "1.6 m",
      "direccionOleaje": "Suroeste",
      "temperatura": "15.5°C",
      "condiciones": "Con viento moderado y oleaje moderado, es un buen momento para disfrutar del SUP.",
      "nivel": "Principiante"
    },
    {
      "hora": "21:00",
      "viento": "9.6 km/h",
      "direccionViento": "Suroeste",
      "direccionVientoGrados": 236,
      "oleaje": "1.62 m",
      "direccionOleaje": "Suroeste",
      "temperatura": "15.4°C",
      "condiciones": "Con viento ligero y oleaje moderado, es adecuado para principiantes.",
      "nivel": "Principiante"
    }
  ],
  "mañana": [
    {
      "hora": "06:00",
      "viento": "5 km/h",
      "direccionViento": "Sur",
      "direccionVientoGrados": 201,
      "oleaje": "1.54 m",
      "direccionOleaje": "Suroeste",
      "temperatura": "14.7°C",
      "condiciones": "Con viento muy ligero y oleaje moderado, es seguro para principiantes.",
      "nivel": "Principiante"
    },
    {
      "hora": "09:00",
      "viento": "4.3 km/h",
      "direccionViento": "Oeste",
      "direccionVientoGrados": 265,
      "oleaje": "1.46 m",
      "direccionOleaje": "Suroeste",
      "temperatura": "14.9°C",
      "condiciones": "Con viento muy ligero y oleaje moderado, es ideal para principiantes.",
      "nivel": "Principiante"
    },
    {
      "hora": "12:00",
      "viento": "9.1 km/h",
      "direccionViento": "Oeste",
      "direccionVientoGrados": 277,
      "oleaje": "1.42 m",
      "direccionOleaje": "Suroeste",
      "temperatura": "15.0°C",
      "condiciones": "Con viento ligero y oleaje moderado, es un buen momento para practicar SUP.",
      "nivel": "Principiante"
    },
    {
      "hora": "15:00",
      "viento": "11.3 km/h",
      "direccionViento": "Suroeste",
      "direccionVientoGrados": 243,
      "oleaje": "1.46 m",
      "direccionOleaje": "Suroeste",
      "temperatura": "15.4°C",
      "condiciones": "Con viento moderado y oleaje moderado, es adecuado para practicar SUP.",
      "nivel": "Principiante"
    },
    {
      "hora": "18:00",
      "viento": "19.9 km/h",
      "direccionViento": "Suroeste",
      "direccionVientoGrados": 226,
      "oleaje": "1.48 m",
      "direccionOleaje": "Suroeste",
      "temperatura": "15.5°C",
      "condiciones": "Con viento fuerte y oleaje moderado, se recomienda precaución para principiantes.",
      "nivel": "Intermedio"
    },
    {
      "hora": "21:00",
      "viento": "14.9 km/h",
      "direccionViento": "Suroeste",
      "direccionVientoGrados": 212,
      "oleaje": "1.48 m",
      "direccionOleaje": "Suroeste",
      "temperatura": "15.5°C",
      "condiciones": "Con viento moderado y oleaje moderado, es un buen momento para disfrutar del SUP.",
      "nivel": "Principiante"
    }
  ],
  "mareas": [],
  "generado": "2025-11-07 04:16:39"
}