{
  "hoy": [
    {
      "hora": "06:00",
      "viento": "1.8 km/h",
      "oleaje": "1.06 m",
      "direccionOleaje": "Suroeste",
      "temperatura": "9.1°C",
      "direccionViento": "Oeste",
      "direccionVientoGrados": 281,
      "nivel": "Principiante",
      "condiciones": "El viento es muy suave, pero el oleaje es un poco alto; podría ser complicado para principiantes."
    },
    {
      "hora": "09:00",
      "viento": "1.8 km/h",
      "oleaje": "1.04 m",
      "direccionOleaje": "Suroeste",
      "temperatura": "12.5°C",
      "direccionViento": "Noroeste",
      "direccionVientoGrados": 294,
      "nivel": "Principiante",
      "condiciones": "Condiciones similares a las de las 6:00; el oleaje sigue siendo un desafío para los principiantes."
    },
    {
      "hora": "12:00",
      "viento": "14.8 km/h",
      "oleaje": "1.0 m",
      "direccionOleaje": "Suroeste",
      "temperatura": "16.5°C",
      "direccionViento": "Norte",
      "direccionVientoGrados": 355,
      "nivel": "Intermedio",
      "condiciones": "El viento ha aumentado, lo que puede ofrecer una buena experiencia para intermedios, pero el oleaje sigue presente."
    },
    {
      "hora": "15:00",
      "viento": "12.1 km/h",
      "oleaje": "0.94 m",
      "direccionOleaje": "Suroeste",
      "temperatura": "17.8°C",
      "direccionViento": "Norte",
      "direccionVientoGrados": 3,
      "nivel": "Intermedio",
      "condiciones": "Las condiciones son favorables para los intermedios, con un oleaje más manejable."
    },
    {
      "hora": "18:00",
      "viento": "4.2 km/h",
      "oleaje": "0.92 m",
      "direccionOleaje": "Suroeste",
      "temperatura": "15.8°C",
      "direccionViento": "Noroeste",
      "direccionVientoGrados": 310,
      "nivel": "Principiante",
      "condiciones": "El viento es suave, y el oleaje es adecuado para principiantes; una buena hora para salir."
    },
    {
      "hora": "21:00",
      "viento": "0.7 km/h",
      "oleaje": "0.88 m",
      "direccionOleaje": "Suroeste",
      "temperatura": "13.8°C",
      "direccionViento": "Oeste",
      "direccionVientoGrados": 284,
      "nivel": "Principiante",
      "condiciones": "El viento es casi inexistente, lo que hace que esta sea una buena oportunidad para practicar."
    }
  ],
  "mañana": [
    {
      "hora": "06:00",
      "viento": "0.4 km/h",
      "oleaje": "0.92 m",
      "direccionOleaje": "Suroeste",
      "temperatura": "11.6°C",
      "direccionViento": "Sureste",
      "direccionVientoGrados": 153,
      "nivel": "Principiante",
      "condiciones": "El viento es muy ligero, pero el oleaje puede ser un poco desafiante para los principiantes."
    },
    {
      "hora": "09:00",
      "viento": "1.1 km/h",
      "oleaje": "0.94 m",
      "direccionOleaje": "Suroeste",
      "temperatura": "15.4°C",
      "direccionViento": "Oeste",
      "direccionVientoGrados": 279,
      "nivel": "Principiante",
      "condiciones": "Condiciones similares a las 6:00, aún un poco complicado para los que están comenzando."
    },
    {
      "hora": "12:00",
      "viento": "11.5 km/h",
      "oleaje": "0.9 m",
      "direccionOleaje": "Suroeste",
      "temperatura": "20.5°C",
      "direccionViento": "Noroeste",
      "direccionVientoGrados": 326,
      "nivel": "Intermedio",
      "condiciones": "El viento ha aumentado, lo que ofrece una buena oportunidad para los intermedios con oleaje manejable."
    },
    {
      "hora": "15:00",
      "viento": "11.3 km/h",
      "oleaje": "0.88 m",
      "direccionOleaje": "Suroeste",
      "temperatura": "21.4°C",
      "direccionViento": "Norte",
      "direccionVientoGrados": 343,
      "nivel": "Intermedio",
      "condiciones": "Las condiciones son óptimas para intermedios, con buen viento y oleaje adecuado."
    },
    {
      "hora": "18:00",
      "viento": "4.5 km/h",
      "oleaje": "0.86 m",
      "direccionOleaje": "Suroeste",
      "temperatura": "17.2°C",
      "direccionViento": "Oeste",
      "direccionVientoGrados": 286,
      "nivel": "Principiante",
      "condiciones": "El viento es suave y el oleaje es amigable para principiantes; buen momento para salir."
    },
    {
      "hora": "21:00",
      "viento": "3.9 km/h",
      "oleaje": "0.86 m",
      "direccionOleaje": "Suroeste",
      "temperatura": "13.5°C",
      "direccionViento": "Oeste",
      "direccionVientoGrados": 248,
      "nivel": "Principiante",
      "condiciones": "El viento es ligero, lo que hace que sea un buen momento para disfrutar del SUP."
    }
  ],
  "mareas": [],
  "generado": "2026-04-28 05:18:00"
}