{
  "generado": "2026-05-08 04:19:23",
  "hoy": [
    {
      "hora": "06:00",
      "viento": "8.7 km/h",
      "oleaje": "3.24 m",
      "direccionOleaje": "Suroeste",
      "temperatura": "11.0°C",
      "direccionViento": "Noroeste",
      "direccionVientoGrados": 336,
      "nivel": "Intermedio",
      "condiciones": "No es un buen momento para SUP debido al oleaje alto."
    },
    {
      "hora": "09:00",
      "viento": "13.5 km/h",
      "oleaje": "3.2 m",
      "direccionOleaje": "Suroeste",
      "temperatura": "14.3°C",
      "direccionViento": "Norte",
      "direccionVientoGrados": 16,
      "nivel": "Intermedio",
      "condiciones": "Las condiciones son desafiantes, mejor esperar a que baje el oleaje."
    },
    {
      "hora": "12:00",
      "viento": "15.0 km/h",
      "oleaje": "3.16 m",
      "direccionOleaje": "Suroeste",
      "temperatura": "17.2°C",
      "direccionViento": "Norte",
      "direccionVientoGrados": 353,
      "nivel": "Intermedio",
      "condiciones": "El oleaje sigue siendo alto, no recomendado para principiantes."
    },
    {
      "hora": "15:00",
      "viento": "18.0 km/h",
      "oleaje": "3.12 m",
      "direccionOleaje": "Suroeste",
      "temperatura": "17.3°C",
      "direccionViento": "Norte",
      "direccionVientoGrados": 344,
      "nivel": "Avanzado",
      "condiciones": "Condiciones avanzadas, solo para paddlers experimentados."
    },
    {
      "hora": "18:00",
      "viento": "12.8 km/h",
      "oleaje": "3.02 m",
      "direccionOleaje": "Suroeste",
      "temperatura": "14.7°C",
      "direccionViento": "Norte",
      "direccionVientoGrados": 355,
      "nivel": "Intermedio",
      "condiciones": "El oleaje comienza a bajar, pero sigue siendo arriesgado."
    },
    {
      "hora": "21:00",
      "viento": "11.9 km/h",
      "oleaje": "2.92 m",
      "direccionOleaje": "Suroeste",
      "temperatura": "13.8°C",
      "direccionViento": "Norte",
      "direccionVientoGrados": 357,
      "nivel": "Intermedio",
      "condiciones": "Condiciones mejorando, pero el oleaje aún es considerable."
    }
  ],
  "mañana": [
    {
      "hora": "06:00",
      "viento": "6.2 km/h",
      "oleaje": "2.54 m",
      "direccionOleaje": "Suroeste",
      "temperatura": "13.3°C",
      "direccionViento": "Este",
      "direccionVientoGrados": 68,
      "nivel": "Principiante",
      "condiciones": "Condiciones suaves, ideal para principiantes."
    },
    {
      "hora": "09:00",
      "viento": "6.9 km/h",
      "oleaje": "2.36 m",
      "direccionOleaje": "Suroeste",
      "temperatura": "15.4°C",
      "direccionViento": "Sureste",
      "direccionVientoGrados": 131,
      "nivel": "Principiante",
      "condiciones": "Las condiciones siguen siendo favorables para nuevos paddlers."
    },
    {
      "hora": "12:00",
      "viento": "5.6 km/h",
      "oleaje": "2.24 m",
      "direccionOleaje": "Suroeste",
      "temperatura": "18.6°C",
      "direccionViento": "Noroeste",
      "direccionVientoGrados": 297,
      "nivel": "Principiante",
      "condiciones": "Excelente momento para disfrutar del SUP con oleaje moderado."
    },
    {
      "hora": "15:00",
      "viento": "14.4 km/h",
      "oleaje": "2.18 m",
      "direccionOleaje": "Suroeste",
      "temperatura": "19.0°C",
      "direccionViento": "Oeste",
      "direccionVientoGrados": 260,
      "nivel": "Intermedio",
      "condiciones": "Condiciones adecuadas, ideal para paddlers intermedios."
    },
    {
      "hora": "18:00",
      "viento": "16.6 km/h",
      "oleaje": "2.14 m",
      "direccionOleaje": "Suroeste",
      "temperatura": "16.4°C",
      "direccionViento": "Suroeste",
      "direccionVientoGrados": 214,
      "nivel": "Avanzado",
      "condiciones": "Condiciones desafiantes, solo para paddlers experimentados."
    },
    {
      "hora": "21:00",
      "viento": "12.3 km/h",
      "oleaje": "2.08 m",
      "direccionOleaje": "Suroeste",
      "temperatura": "14.0°C",
      "direccionViento": "Sur",
      "direccionVientoGrados": 185,
      "nivel": "Intermedio",
      "condiciones": "El oleaje está disminuyendo, condiciones aceptables para intermedios."
    }
  ],
  "mareas": [
    {
      "hora": "19:00",
      "altura": 1.3,
      "tipo": "alta"
    },
    {
      "hora": "01:12",
      "altura": 0.5,
      "tipo": "baja"
    },
    {
      "hora": "07:25",
      "altura": 1.2,
      "tipo": "alta"
    },
    {
      "hora": "13:37",
      "altura": 0.4,
      "tipo": "baja"
    }
  ]
}