{
  "hoy": [
    {
      "hora": "06:00",
      "viento": "7.4 km/h",
      "oleaje": "1.32 m",
      "direccionOleaje": "Suroeste",
      "temperatura": "12.4°C",
      "direccionViento": "Noreste",
      "direccionVientoGrados": 51,
      "nivel": "Principiante",
      "condiciones": "Las condiciones son adecuadas para principiantes, con poco viento y oleaje moderado."
    },
    {
      "hora": "09:00",
      "viento": "5.9 km/h",
      "oleaje": "1.4 m",
      "direccionOleaje": "Suroeste",
      "temperatura": "12.7°C",
      "direccionViento": "Noreste",
      "direccionVientoGrados": 35,
      "nivel": "Principiante",
      "condiciones": "Es un buen momento para iniciarse en el SUP, el viento es suave."
    },
    {
      "hora": "12:00",
      "viento": "6.7 km/h",
      "oleaje": "1.52 m",
      "direccionOleaje": "Suroeste",
      "temperatura": "16.1°C",
      "direccionViento": "Noroeste",
      "direccionVientoGrados": 326,
      "nivel": "Principiante",
      "condiciones": "Las condiciones son favorables para principiantes, con oleaje ligero."
    },
    {
      "hora": "15:00",
      "viento": "12.5 km/h",
      "oleaje": "1.66 m",
      "direccionOleaje": "Suroeste",
      "temperatura": "16.6°C",
      "direccionViento": "Noroeste",
      "direccionVientoGrados": 323,
      "nivel": "Intermedio",
      "condiciones": "El viento es un poco más fuerte, ideal para intermedios que buscan un desafío."
    },
    {
      "hora": "18:00",
      "viento": "6.5 km/h",
      "oleaje": "1.8 m",
      "direccionOleaje": "Suroeste",
      "temperatura": "14.8°C",
      "direccionViento": "Noroeste",
      "direccionVientoGrados": 326,
      "nivel": "Principiante",
      "condiciones": "A esta hora, las condiciones son relajadas, perfectas para principiantes."
    },
    {
      "hora": "21:00",
      "viento": "2.8 km/h",
      "oleaje": "1.9 m",
      "direccionOleaje": "Suroeste",
      "temperatura": "13.0°C",
      "direccionViento": "Norte",
      "direccionVientoGrados": 15,
      "nivel": "Principiante",
      "condiciones": "Las condiciones son tranquilas, ideales para una sesión nocturna de SUP."
    }
  ],
  "mañana": [
    {
      "hora": "06:00",
      "viento": "19.7 km/h",
      "oleaje": "1.96 m",
      "direccionOleaje": "Suroeste",
      "temperatura": "13.7°C",
      "direccionViento": "Norte",
      "direccionVientoGrados": 6,
      "nivel": "Avanzado",
      "condiciones": "Condiciones desafiantes, adecuadas solo para paddlers avanzados."
    },
    {
      "hora": "09:00",
      "viento": "14.1 km/h",
      "oleaje": "1.94 m",
      "direccionOleaje": "Suroeste",
      "temperatura": "15.9°C",
      "direccionViento": "Norte",
      "direccionVientoGrados": 357,
      "nivel": "Intermedio",
      "condiciones": "Ideal para intermedios, con viento moderado y oleaje manejable."
    },
    {
      "hora": "12:00",
      "viento": "16.7 km/h",
      "oleaje": "1.94 m",
      "direccionOleaje": "Suroeste",
      "temperatura": "17.7°C",
      "direccionViento": "Norte",
      "direccionVientoGrados": 349,
      "nivel": "Avanzado",
      "condiciones": "Condiciones óptimas para los más experimentados, con buen viento."
    },
    {
      "hora": "15:00",
      "viento": "15.8 km/h",
      "oleaje": "1.92 m",
      "direccionOleaje": "Suroeste",
      "temperatura": "17.4°C",
      "direccionViento": "Norte",
      "direccionVientoGrados": 345,
      "nivel": "Avanzado",
      "condiciones": "Las condiciones son ideales para un SUP desafiante, con viento fuerte."
    },
    {
      "hora": "18:00",
      "viento": "14.1 km/h",
      "oleaje": "1.92 m",
      "direccionOleaje": "Suroeste",
      "temperatura": "15.4°C",
      "direccionViento": "Norte",
      "direccionVientoGrados": 343,
      "nivel": "Intermedio",
      "condiciones": "A esta hora, es perfecto para intermedios que buscan mejorar sus habilidades."
    },
    {
      "hora": "21:00",
      "viento": "1.6 km/h",
      "oleaje": "1.88 m",
      "direccionOleaje": "Suroeste",
      "temperatura": "14.1°C",
      "direccionViento": "Norte",
      "direccionVientoGrados": 6,
      "nivel": "Principiante",
      "condiciones": "Condiciones suaves, ideales para disfrutar de un paseo tranquilo en la noche."
    }
  ],
  "mareas": [],
  "generado": "2026-05-04 05:15:19"
}