{
  "hoy": [
    {
      "hora": "06:00",
      "viento": "10.0 km/h",
      "oleaje": "1.48 m",
      "direccionOleaje": "Suroeste",
      "temperatura": "14.8°C",
      "direccionViento": "Sureste",
      "direccionVientoGrados": 150,
      "nivel": "Intermedio",
      "condiciones": "Las condiciones son moderadas, ideales para principiantes que buscan practicar."
    },
    {
      "hora": "09:00",
      "viento": "14.1 km/h",
      "oleaje": "1.4 m",
      "direccionOleaje": "Suroeste",
      "temperatura": "15.0°C",
      "direccionViento": "Sur",
      "direccionVientoGrados": 167,
      "nivel": "Intermedio",
      "condiciones": "Aumento en el viento, buen momento para intermedios que buscan un poco de desafío."
    },
    {
      "hora": "12:00",
      "viento": "19.8 km/h",
      "oleaje": "1.38 m",
      "direccionOleaje": "Suroeste",
      "temperatura": "17.2°C",
      "direccionViento": "Sur",
      "direccionVientoGrados": 183,
      "nivel": "Avanzado",
      "condiciones": "Condiciones avanzadas, perfectas para paddlers experimentados que buscan adrenalina."
    },
    {
      "hora": "15:00",
      "viento": "24.2 km/h",
      "oleaje": "1.52 m",
      "direccionOleaje": "Suroeste",
      "temperatura": "16.5°C",
      "direccionViento": "Suroeste",
      "direccionVientoGrados": 213,
      "nivel": "Avanzado",
      "condiciones": "El viento fuerte y el oleaje son ideales para quienes buscan un reto serio."
    },
    {
      "hora": "18:00",
      "viento": "23.5 km/h",
      "oleaje": "1.82 m",
      "direccionOleaje": "Suroeste",
      "temperatura": "15.8°C",
      "direccionViento": "Sur",
      "direccionVientoGrados": 198,
      "nivel": "Avanzado",
      "condiciones": "Condiciones desafiantes, solo para paddlers con experiencia que buscan emociones."
    },
    {
      "hora": "21:00",
      "viento": "15.5 km/h",
      "oleaje": "2.06 m",
      "direccionOleaje": "Suroeste",
      "temperatura": "15.0°C",
      "direccionViento": "Sur",
      "direccionVientoGrados": 181,
      "nivel": "Avanzado",
      "condiciones": "Las condiciones son fuertes, recomendadas para los más experimentados."
    }
  ],
  "mañana": [
    {
      "hora": "06:00",
      "viento": "12.8 km/h",
      "oleaje": "2.52 m",
      "direccionOleaje": "Suroeste",
      "temperatura": "14.6°C",
      "direccionViento": "Sur",
      "direccionVientoGrados": 164,
      "nivel": "Intermedio",
      "condiciones": "Condiciones adecuadas para intermedios, pero con precaución debido al oleaje."
    },
    {
      "hora": "09:00",
      "viento": "13.1 km/h",
      "oleaje": "2.58 m",
      "direccionOleaje": "Suroeste",
      "temperatura": "14.9°C",
      "direccionViento": "Sur",
      "direccionVientoGrados": 172,
      "nivel": "Intermedio",
      "condiciones": "Aumento en el oleaje, recomendado para quienes tienen algo de experiencia."
    },
    {
      "hora": "12:00",
      "viento": "21.3 km/h",
      "oleaje": "2.62 m",
      "direccionOleaje": "Suroeste",
      "temperatura": "16.1°C",
      "direccionViento": "Sur",
      "direccionVientoGrados": 199,
      "nivel": "Avanzado",
      "condiciones": "Condiciones desafiantes, perfectas para paddlers avanzados en busca de emoción."
    },
    {
      "hora": "15:00",
      "viento": "25.0 km/h",
      "oleaje": "2.7 m",
      "direccionOleaje": "Suroeste",
      "temperatura": "15.8°C",
      "direccionViento": "Suroeste",
      "direccionVientoGrados": 207,
      "nivel": "Avanzado",
      "condiciones": "El viento y oleaje son intensos, solo para los más experimentados."
    },
    {
      "hora": "18:00",
      "viento": "20.3 km/h",
      "oleaje": "2.74 m",
      "direccionOleaje": "Suroeste",
      "temperatura": "15.0°C",
      "direccionViento": "Sur",
      "direccionVientoGrados": 200,
      "nivel": "Avanzado",
      "condiciones": "Condiciones muy desafiantes, ideales para quienes buscan un gran reto."
    },
    {
      "hora": "21:00",
      "viento": "15.5 km/h",
      "oleaje": "2.7 m",
      "direccionOleaje": "Suroeste",
      "temperatura": "14.5°C",
      "direccionViento": "Sur",
      "direccionVientoGrados": 183,
      "nivel": "Avanzado",
      "condiciones": "Las condiciones son fuertes, perfectas para paddlers experimentados que buscan aventura."
    }
  ],
  "mareas": [],
  "generado": "2026-04-22 04:27:54"
}